{"result":[{"hrPow":0,"logHr":"00"},{"hrPow":0,"logHr":"01"},{"hrPow":0,"logHr":"02"},{"hrPow":0,"logHr":"03"},{"hrPow":0,"logHr":"04"},{"hrPow":0,"logHr":"05"},{"hrPow":100,"logHr":"06"},{"hrPow":8100,"logHr":"07"},{"hrPow":32000,"logHr":"08"},{"hrPow":54400,"logHr":"09"},{"hrPow":51300,"logHr":"10"},{"hrPow":67500,"logHr":"11"},{"hrPow":75800,"logHr":"12"},{"hrPow":71000,"logHr":"13"},{"hrPow":54200,"logHr":"14"},{"hrPow":37000,"logHr":"15"},{"hrPow":9600,"logHr":"16"},{"hrPow":0,"logHr":"18"},{"hrPow":0,"logHr":"19"},{"hrPow":0,"logHr":"20"},{"hrPow":0,"logHr":"21"},{"hrPow":0,"logHr":"22"}]}